coorx/__init__.py
coorx/_types.py
coorx/base_transform.py
coorx/composite.py
coorx/coordinates.py
coorx/events.py
coorx/image.py
coorx/linear.py
coorx/matrices.py
coorx/nonlinear.py
coorx/params.py
coorx/qt.py
coorx/systems.py
coorx/util.py
coorx-2.0.0.dist-info/licenses/LICENSE.txt
coorx-2.0.0.dist-info/METADATA
coorx-2.0.0.dist-info/WHEEL
coorx-2.0.0.dist-info/top_level.txt
coorx-2.0.0.dist-info/RECORD
