Metadata-Version: 2.4
Name: coorx
Version: 2.0.0
Summary: Object-oriented linear and nonlinear coordinate system transforms, plus coordinate system graphs.
Home-page: http://github.com/campagnola/coorx
Author: Luke Campagnola
Author-email: lukec@alleninstitute.org
License: BSD
Classifier: Programming Language :: Python :: 3
Classifier: License :: OSI Approved :: BSD License
Classifier: Operating System :: OS Independent
License-File: LICENSE.txt
Dynamic: author
Dynamic: author-email
Dynamic: classifier
Dynamic: description
Dynamic: description-content-type
Dynamic: home-page
Dynamic: license
Dynamic: license-file
Dynamic: summary
